gcal/__init__.py
gcal/__main__.py
gcal/api.py
gcal/cli.py
gcal/commands/__init__.py
gcal/commands/calendars.py
gcal/commands/events.py
rlane_gcal-1.0.5.dist-info/METADATA
rlane_gcal-1.0.5.dist-info/WHEEL
rlane_gcal-1.0.5.dist-info/entry_points.txt
rlane_gcal-1.0.5.dist-info/licenses/LICENSE
rlane_gcal-1.0.5.dist-info/RECORD
