Metadata-Version: 2.1
Name: rlane-gcal
Version: 1.0.5
Summary: Google Calendar CLI
Keywords: google,calendar,gcal
Author-Email: Russel Lane <russel@rlane.com>
License: MIT
Classifier: Development Status :: 4 - Beta
Classifier: Intended Audience :: End Users/Desktop
Classifier: License :: OSI Approved :: MIT License
Classifier: Programming Language :: Python :: 3
Project-URL: Homepage, https://github.com/russellane/gcal
Requires-Python: >=3.10
Requires-Dist: dateparser>=1.2.0
Requires-Dist: loguru>=0.7.3
Requires-Dist: rich>=13.9.4
Requires-Dist: rlane-libcli>=1.0.8
Requires-Dist: rlane-libgoogle>=1.0.2
